md2html/__init__.py
md2html/bin.py
md2html/core.py
md2html/utils.py
md2html/version.json
md2html/template/default.html
md2html/template/pygments.css
md2html/template/styles.css
md2html_python-1.0.2.dist-info/METADATA
md2html_python-1.0.2.dist-info/WHEEL
md2html_python-1.0.2.dist-info/entry_points.txt
md2html_python-1.0.2.dist-info/top_level.txt
md2html_python-1.0.2.dist-info/RECORD
