Metadata-Version: 2.4
Name: md2html-python
Version: 1.0.2
Summary: A user-friendly tool for converting Markdown to HTML
Home-page: https://github.com/suqingdong/markdown_to_docx
Author: suqingdong
Author-email: suqingdong1114@gmail.com
License: MIT License
Classifier: Development Status :: 5 - Production/Stable
Classifier: Operating System :: OS Independent
Classifier: Intended Audience :: Developers
Classifier: Programming Language :: Python
Classifier: Programming Language :: Python :: 3
Classifier: Programming Language :: Python :: 3.9
Classifier: Programming Language :: Python :: 3.10
Classifier: Programming Language :: Python :: 3.11
Classifier: Programming Language :: Python :: 3.12
Classifier: Topic :: Software Development :: Libraries
Requires-Dist: click
Requires-Dist: markdown
Requires-Dist: pymdown-extensions
Requires-Dist: pygments
Requires-Dist: jinja2
Requires-Dist: loguru
Dynamic: author
Dynamic: author-email
Dynamic: classifier
Dynamic: description
Dynamic: description-content-type
Dynamic: home-page
Dynamic: license
Dynamic: requires-dist
Dynamic: summary
